haychecker/__init__.py
haychecker/_common/__init__.py
haychecker/_common/_task.py
haychecker/_common/config.py
haychecker/_test/__init__.py
haychecker/_test/chc/__init__.py
haychecker/_test/chc/completeness_test.py
haychecker/_test/chc/constraint_test.py
haychecker/_test/chc/deduplication_test.py
haychecker/_test/chc/entropy_test.py
haychecker/_test/chc/freshness_test.py
haychecker/_test/chc/grouprule_test.py
haychecker/_test/chc/mutual_info_test.py
haychecker/_test/chc/rule_test.py
haychecker/_test/chc/runtime_checks_test.py
haychecker/_test/chc/task_test.py
haychecker/_test/chc/timeliness_test.py
haychecker/_test/common/__init__.py
haychecker/_test/common/config_test.py
haychecker/_test/dhc/__init__.py
haychecker/_test/dhc/completeness_test.py
haychecker/_test/dhc/constraint_test.py
haychecker/_test/dhc/deduplication_approximated_test.py
haychecker/_test/dhc/deduplication_test.py
haychecker/_test/dhc/entropy_test.py
haychecker/_test/dhc/freshness_test.py
haychecker/_test/dhc/grouprule_test.py
haychecker/_test/dhc/mutual_info_test.py
haychecker/_test/dhc/rule_test.py
haychecker/_test/dhc/runtime_checks_test.py
haychecker/_test/dhc/task_test.py
haychecker/_test/dhc/timeliness_test.py
haychecker/chc/__init__.py
haychecker/chc/_runtime_checks.py
haychecker/chc/metrics.py
haychecker/chc/task.py
haychecker/dhc/__init__.py
haychecker/dhc/_runtime_checks.py
haychecker/dhc/metrics.py
haychecker/dhc/task.py
haychecker-0.0.1.dist-info/METADATA
haychecker-0.0.1.dist-info/RECORD
haychecker-0.0.1.dist-info/WHEEL
haychecker-0.0.1.dist-info/top_level.txt
